{"_embedded":{"events":[{"properties":{"vehicle-type":"truck"},"measures":[{"tag":"direction","value":266.0,"unit":"DEGREE"},{"tag":"speed","value":13.0,"unit":"MPS"},{"tag":"vehicleCount","value":7.0,"unit":null}],"event-uid":"71dd5a79-c437-4e91-bf9d-0ee3dceb6a01","timestamp":1462925168327,"event-type":"TFEVT","device-uid":"HYP1040-75","location-uid":"HYP1040-75-Lane2"}]},"_links":{"self":{"href":"http://ie-traffic.run.aws-usw02-pr.ice.predix.io/v1/assets/1000000018/events?event-types=TFEVT&start-ts=1462925163463&end-ts=1462925173463&size=1000"},"next-page":{"href":"http://ie-traffic.run.aws-usw02-pr.ice.predix.io/v1/assets/1000000018/events?event-types=TFEVT&start-ts=0&end-ts=1462925173463&size=1000"}},"page":{"size":1000,"totalElements":1,"totalPages":1,"number":0}}
